config_file/__init__.py
config_file/config_file.py
config_file/config_file_path.py
config_file/exceptions.py
config_file/nested_lookup.py
config_file/parsers/__init__.py
config_file/parsers/abstract_parser.py
config_file/parsers/base_parser.py
config_file/parsers/ini_parser.py
config_file/parsers/json_parser.py
config_file/parsers/parse_value.py
config_file/parsers/toml_parser.py
config_file/parsers/yaml_parser.py
config_file/utils.py
config_file-0.13.1.dist-info/LICENSE
config_file-0.13.1.dist-info/METADATA
config_file-0.13.1.dist-info/WHEEL
config_file-0.13.1.dist-info/RECORD
