Metadata-Version: 2.1
Name: config_file
Version: 0.13.1
Summary: Modify configuration files of various formats with the same simple API.
Home-page: https://github.com/eugenetriguba/config_file
Keywords: configuration,ini,json,toml,yaml
Author: Eugene Triguba
Author-email: eugenetriguba@gmail.com
Requires-Python: >=3.6,<4.0
Classifier: Development Status :: 4 - Beta
Classifier: Intended Audience :: Developers
Classifier: License :: OSI Approved :: MIT License
Classifier: Operating System :: OS Independent
Classifier: Programming Language :: Python :: 3
Classifier: Programming Language :: Python :: 3.6
Classifier: Programming Language :: Python :: 3.7
Classifier: Programming Language :: Python :: 3.8
Classifier: Programming Language :: Python :: 3.9
Classifier: Programming Language :: Python :: 3.10
Classifier: Programming Language :: Python :: 3.11
Classifier: Programming Language :: Python :: 3.12
Classifier: Topic :: Software Development :: Libraries
Classifier: Topic :: Software Development :: Libraries :: Python Modules
Provides-Extra: toml
Provides-Extra: yaml
Requires-Dist: ruamel.yaml (>=0.17.16,<0.18.0) ; extra == "yaml"
Requires-Dist: tomlkit (==0.7.2) ; (python_version >= "3.6" and python_version < "3.7") and (extra == "toml")
Requires-Dist: tomlkit (>=0.12.2,<0.13.0) ; (python_version >= "3.7" and python_version < "4") and (extra == "toml")
Project-URL: Documentation, https://config-file.readthedocs.io/
Project-URL: Repository, https://github.com/eugenetriguba/config_file
